cubexpress/__init__.py
cubexpress/core/__init__.py
cubexpress/core/config.py
cubexpress/core/exceptions.py
cubexpress/core/types.py
cubexpress/download/__init__.py
cubexpress/download/batch.py
cubexpress/download/core.py
cubexpress/download/esa.py
cubexpress/download/merge.py
cubexpress/download/quick.py
cubexpress/download/tiling.py
cubexpress/formats/__init__.py
cubexpress/formats/presets.py
cubexpress/formats/specs.py
cubexpress/geometry/__init__.py
cubexpress/geometry/conversion.py
cubexpress/geometry/roi.py
cubexpress/metadata/__init__.py
cubexpress/metadata/cache.py
cubexpress/metadata/scene.py
cubexpress/metadata/sensors.py
cubexpress/metadata/tables.py
cubexpress/processing/__init__.py
cubexpress/processing/animation.py
cubexpress/processing/qa.py
cubexpress/request/__init__.py
cubexpress/request/builder.py
cubexpress/request/transforms.py
cubexpress/test/__init__.py
cubexpress/test/conftest.py
cubexpress/test/test_cache.py
cubexpress/test/test_cloud_utils.py
cubexpress/test/test_config.py
cubexpress/test/test_conversion.py
cubexpress/test/test_downloader.py
cubexpress/test/test_exceptions.py
cubexpress/test/test_formats.py
cubexpress/test/test_geospatial.py
cubexpress/test/test_geotyping.py
cubexpress/test/test_request.py
cubexpress/test/test_tiling.py
cubexpress/utils/__init__.py
cubexpress/utils/logging.py
cubexpress-0.1.39.dist-info/LICENSE
cubexpress-0.1.39.dist-info/METADATA
cubexpress-0.1.39.dist-info/WHEEL
cubexpress-0.1.39.dist-info/RECORD
