Metadata-Version: 2.1
Name: cubexpress
Version: 0.1.39
Summary: Efficient processing of cubic Earth-observation (EO) data.
Home-page: https://github.com/andesdatacube/cubexpress
Keywords: earth-engine,sentinel-2,geospatial,eo,cube
Author: Julio Contreras
Author-email: contrerasnetk@gmail.com
Requires-Python: >=3.10,<4.0
Classifier: License :: OSI Approved :: MIT License
Classifier: Programming Language :: Python :: 3
Classifier: Programming Language :: Python :: 3.10
Classifier: Programming Language :: Python :: 3.11
Classifier: Programming Language :: Python :: 3.12
Classifier: Programming Language :: Python :: 3 :: Only
Classifier: Topic :: Scientific/Engineering :: GIS
Provides-Extra: esa
Requires-Dist: earthengine-api (>=1.5.12)
Requires-Dist: nest-asyncio (>=1.6.0,<2.0.0) ; extra == "esa"
Requires-Dist: numpy (>=1.26.0,<2.1.0)
Requires-Dist: pandas (>=2.0.0)
Requires-Dist: playwright (>=1.40.0,<2.0.0) ; extra == "esa"
Requires-Dist: pyarrow (>=14.0.0)
Requires-Dist: pydantic (>=2.0.0)
Requires-Dist: pygeohash (>=1.2.0)
Requires-Dist: pyproj (>=3.6.0)
Requires-Dist: rasterio (>=1.3.9)
Requires-Dist: requests (>=2.31.0)
Requires-Dist: tqdm (>=4.65.0)
Requires-Dist: utm (>=0.7.0)
Project-URL: Documentation, https://andesdatacube.github.io/cubexpress
Project-URL: Repository, https://github.com/andesdatacube/cubexpress
